aiddl_common/__init__.py
aiddl_common/aiddl/__init__.py
aiddl_common/aiddl/org/__init__.py
aiddl_common/aiddl/org/aiddl/__init__.py
aiddl_common/aiddl/org/aiddl/common/__init__.py
aiddl_common/aiddl/org/aiddl/common/domain.aiddl
aiddl_common/aiddl/org/aiddl/common/execution/__init__.py
aiddl_common/aiddl/org/aiddl/common/execution/automata/__init__.py
aiddl_common/aiddl/org/aiddl/common/execution/automata/discrete-finite-state-machine.aiddl
aiddl_common/aiddl/org/aiddl/common/learning/__init__.py
aiddl_common/aiddl/org/aiddl/common/learning/supervised.aiddl
aiddl_common/aiddl/org/aiddl/common/learning/supervised/__init__.py
aiddl_common/aiddl/org/aiddl/common/learning/supervised/decision-tree.aiddl
aiddl_common/aiddl/org/aiddl/common/learning/supervised/linear-regression.aiddl
aiddl_common/aiddl/org/aiddl/common/math/__init__.py
aiddl_common/aiddl/org/aiddl/common/math/graph.aiddl
aiddl_common/aiddl/org/aiddl/common/math/linear-algebra.aiddl
aiddl_common/aiddl/org/aiddl/common/optimization/__init__.py
aiddl_common/aiddl/org/aiddl/common/optimization/combinatorial.aiddl
aiddl_common/aiddl/org/aiddl/common/optimization/combinatorial/__init__.py
aiddl_common/aiddl/org/aiddl/common/optimization/combinatorial/knapsack.aiddl
aiddl_common/aiddl/org/aiddl/common/optimization/combinatorial/tsp.aiddl
aiddl_common/aiddl/org/aiddl/common/planning/__init__.py
aiddl_common/aiddl/org/aiddl/common/planning/plan-space.aiddl
aiddl_common/aiddl/org/aiddl/common/planning/state-variable.aiddl
aiddl_common/aiddl/org/aiddl/common/planning/task-network.aiddl
aiddl_common/aiddl/org/aiddl/common/planning/temporal.aiddl
aiddl_common/aiddl/org/aiddl/common/planning/state-variable/__init__.py
aiddl_common/aiddl/org/aiddl/common/planning/state-variable/data.aiddl
aiddl_common/aiddl/org/aiddl/common/planning/state-variable/plan.aiddl
aiddl_common/aiddl/org/aiddl/common/planning/state-variable/state-variable-java.aiddl
aiddl_common/aiddl/org/aiddl/common/planning/state-variable/solver/__init__.py
aiddl_common-0.1.0.dist-info/LICENSE
aiddl_common-0.1.0.dist-info/METADATA
aiddl_common-0.1.0.dist-info/WHEEL
aiddl_common-0.1.0.dist-info/top_level.txt
aiddl_common-0.1.0.dist-info/RECORD
